LICENSE
MANIFEST.in
README.md
pyproject.toml
setup.cfg
src/napari_boids/_BoidFlock.py
src/napari_boids/__init__.py
src/napari_boids/_widget.py
src/napari_boids/napari.yaml
src/napari_boids.egg-info/PKG-INFO
src/napari_boids.egg-info/SOURCES.txt
src/napari_boids.egg-info/dependency_links.txt
src/napari_boids.egg-info/entry_points.txt
src/napari_boids.egg-info/requires.txt
src/napari_boids.egg-info/top_level.txt
src/napari_boids/_tests/__init__.py
src/napari_boids/_tests/test_widget.py