Metadata-Version: 2.1
Name: napari-boids
Version: 0.0.1
Summary: A plugin to look at boids
Home-page: https://github.com/leoguignard/napari-boids
Author: Léo Guignard
Author-email: leo.guignard@univ-amu.fr
License: BSD-3-Clause
Project-URL: Bug Tracker, https://github.com/leoguignard/napari-boids/issues
Project-URL: Documentation, https://github.com/leoguignard/napari-boids#README.md
Project-URL: Source Code, https://github.com/leoguignard/napari-boids
Project-URL: User Support, https://github.com/leoguignard/napari-boids/issues
Classifier: Development Status :: 2 - Pre-Alpha
Classifier: Framework :: napari
Classifier: Intended Audience :: Developers
Classifier: License :: OSI Approved :: BSD License
Classifier: Operating System :: OS Independent
Classifier: Programming Language :: Python
Classifier: Programming Language :: Python :: 3
Classifier: Programming Language :: Python :: 3 :: Only
Classifier: Programming Language :: Python :: 3.8
Classifier: Programming Language :: Python :: 3.9
Classifier: Programming Language :: Python :: 3.10
Classifier: Topic :: Scientific/Engineering :: Image Processing
Requires-Python: >=3.8
Provides-Extra: testing
License-File: LICENSE
